odoo/addons/l10n_nl_tax_statement/README.rst
odoo/addons/l10n_nl_tax_statement/__init__.py
odoo/addons/l10n_nl_tax_statement/__manifest__.py
odoo/addons/l10n_nl_tax_statement/data/paperformat.xml
odoo/addons/l10n_nl_tax_statement/i18n/l10n_nl_tax_statement.pot
odoo/addons/l10n_nl_tax_statement/i18n/nl.po
odoo/addons/l10n_nl_tax_statement/models/__init__.py
odoo/addons/l10n_nl_tax_statement/models/account_move.py
odoo/addons/l10n_nl_tax_statement/models/account_move_line.py
odoo/addons/l10n_nl_tax_statement/models/l10n_nl_vat_statement.py
odoo/addons/l10n_nl_tax_statement/models/l10n_nl_vat_statement_line.py
odoo/addons/l10n_nl_tax_statement/models/res_company.py
odoo/addons/l10n_nl_tax_statement/models/res_config_settings.py
odoo/addons/l10n_nl_tax_statement/readme/CONFIGURE.md
odoo/addons/l10n_nl_tax_statement/readme/CONTRIBUTORS.md
odoo/addons/l10n_nl_tax_statement/readme/DESCRIPTION.md
odoo/addons/l10n_nl_tax_statement/readme/ROADMAP.md
odoo/addons/l10n_nl_tax_statement/readme/USAGE.md
odoo/addons/l10n_nl_tax_statement/report/__init__.py
odoo/addons/l10n_nl_tax_statement/report/l10n_nl_tax_statement_xlsx.py
odoo/addons/l10n_nl_tax_statement/report/report_tax_statement.xml
odoo/addons/l10n_nl_tax_statement/security/ir.model.access.csv
odoo/addons/l10n_nl_tax_statement/security/tax_statement_security_rule.xml
odoo/addons/l10n_nl_tax_statement/static/description/icon.png
odoo/addons/l10n_nl_tax_statement/static/description/index.html
odoo/addons/l10n_nl_tax_statement/static/src/css/report.css
odoo/addons/l10n_nl_tax_statement/tests/__init__.py
odoo/addons/l10n_nl_tax_statement/tests/test_l10n_nl_vat_statement.py
odoo/addons/l10n_nl_tax_statement/views/l10n_nl_vat_statement_view.xml
odoo/addons/l10n_nl_tax_statement/views/report_tax_statement.xml
odoo/addons/l10n_nl_tax_statement/views/res_config_settings.xml
odoo_addon_l10n_nl_tax_statement-18.0.1.0.0.4.dist-info/METADATA
odoo_addon_l10n_nl_tax_statement-18.0.1.0.0.4.dist-info/WHEEL
odoo_addon_l10n_nl_tax_statement-18.0.1.0.0.4.dist-info/top_level.txt
odoo_addon_l10n_nl_tax_statement-18.0.1.0.0.4.dist-info/RECORD
